[
    {
        "patchName": "Custom branding name for YouTube",
        "options": [
            {
                "key": "AppName",
                "value": "YouTube RVX"
            }
        ]
    },
    {
        "patchName": "Custom branding name for YouTube Music",
        "options": [
            {
                "key": "AppNameNotification",
                "value": "YouTube Music RVX"
            },
            {
                "key": "AppNameLauncher",
                "value": "YouTube Music RVX"
            }
        ]
    },
    {
        "patchName": "Custom branding name for Reddit",
        "options": [
            {
                "key": "AppName",
                "value": "Reddit RVX"
            }
        ]
    },
    {
        "patchName": "Change package name",
        "options": [
            {
                "key": "PackageNameReddit",
                "value": "reddit.rvx.seanti.exe"
            }
        ]
    }
]
